YOTRACO/__init__.py
YOTRACO/yotraco.py
YOTRACO/yotracoStats.py
yotraco-0.2.4.dist-info/licenses/LICENSE
yotraco-0.2.4.dist-info/METADATA
yotraco-0.2.4.dist-info/WHEEL
yotraco-0.2.4.dist-info/top_level.txt
yotraco-0.2.4.dist-info/RECORD
