Metadata-Version: 2.4
Name: yotraco
Version: 0.2.4
Summary: A YOLO-based object tracking and counting system.
Home-page: https://github.com/NEREUS-code/YOTRACO
Author: YOTRACO TEAM
Author-email: YOTRACO TEAM <nereuscode@gmail.com>
License: MIT
Project-URL: Homepage, https://github.com/NEREUS-code/YOTRACO
Requires-Python: >=3.8
License-File: LICENSE
Requires-Dist: torch
Requires-Dist: opencv-python
Requires-Dist: ultralytics
Requires-Dist: matplotlib
Dynamic: author
Dynamic: home-page
Dynamic: license-file
Dynamic: requires-python
